neutralNEMO/__init__.py
neutralNEMO/eos.py
neutralNEMO/grid.py
neutralNEMO/surf.py
neutralnemo-1.1.0.dist-info/METADATA
neutralnemo-1.1.0.dist-info/WHEEL
neutralnemo-1.1.0.dist-info/licenses/LICENSE
neutralnemo-1.1.0.dist-info/RECORD
