Metadata-Version: 2.3
Name: neutralNEMO
Version: 1.1.0
Summary: A package to calculate approximate neutral surfaces with NEMO model output
Project-URL: Homepage, https://github.com/afstyles/neutralNEMO
Project-URL: Issues, https://github.com/afstyles/neutralNEMO/issues
Author-email: Andrew Styles <afstylesocean@gmail.com>
License-File: LICENSE
Classifier: License :: OSI Approved :: MIT License
Classifier: Operating System :: OS Independent
Classifier: Programming Language :: Python :: 3
Requires-Python: >=3.8
Requires-Dist: neutralocean>=2.1.2
